{
    "elements": [
        {
            "name": "bar",
            "from": [-2,11.75,0],
            "to": [18,13.75,2],
            "uv": [0,42],
            "origin": [8,13.75,1],
            "scale": 0.667
        },
        {
            "name": "banner",
            "from": [-2,-26.25,2],
            "to": [18,13.75,3],
            "uv": [0,0],
            "origin": [8,13.75,1],
            "rotation": [-0.5,0,0],
            "scale": 0.667
        }
    ],
    "animations": {
        "idle": {
            "script": "banner_sway",
            "with": { "banner": "banner" }
        }
    }
}